{
    "title": "aaDum chidhambaramO",
    "language": "Tamil",
    "raga": "behaag",
    "tala": "aadi",
    "composer": "GOpaalakrishna-Bhaaratiyaar",
    "sahitya": "ADum cidambaramO ayyan kUttADum cidambaramO \n\n(ADum)\n\n\n\nanupallavi\n\n\n\nAdum cidambaram anbar kaLikkavE nAdum cidambaram\n\nnamashivAyavenru \n\n(ADum)\n\n\n\ncaraNam 1\n\n\n\nyArum ariyAmal ambala vANanAr shIraDiyAr pArkka sEvaDi tUkki\n\nninru \n\n(Adum)\n\n\n\ncaraNam 2\n\n\n\nbAlakrSnan pOTrum panimadi shaDaiyinAr tALa maddaLam\n\npODa tAttattai enavE \n\n(ADum)",
    "src": "https:\/\/karnatik.com\/c1217.shtml"
}