{
    "title": "ADinayE kaNNaa",
    "language": "Tamil",
    "raga": "mOhana-kalyaaNi",
    "tala": "aadi",
    "composer": "Ambujam-Krishna",
    "sahitya": "ADinaiyE kaNNA brndAvanam tanil Ananda rasamaya arputa naTanam\r\n\r\nanupallavi\r\n\r\nIdilA azhagiyar gOpiyar unaittEDi nADi vandiDa nadikkarai nilavoLiyil\r\n\r\ncaraNam\r\n\r\nmayil pIli shaTrE koNDai tanil ashaiya navaratna makuTam shiram tanil oLira\r\n makara kuNDalangaL iru shevi ilanga matimukham tanilE muruval viLaiyADa\r\n maNam kamazh mAlaigaL mArbil ashaindADa mayangum andivaNNa Adai iDaiyADa\r\n madhura mOhana kuzhal ishai kUTTa mangaiyar kaNgaL maiyyal kATTa\r\n malar kamazh shalangai jati layam kUTTa manamarindu aruL shorindu iNaindu onrAi",
    "src": "https:\/\/karnatik.com\/c3325.shtml"
}