{
    "title": "aiyappanai paNivOm",
    "language": "Tamil",
    "raga": "Arabhi",
    "tala": "Arabhi",
    "composer": "Paapanaasam-Shivan",
    "sahitya": "aiyappanai paNivOm ulagIl koDum asura samhAr-AvatAra mUrtiyAm \n\n\nanupallavi\n\n  mei anbargaL manam virumbum varam tara mEdini engum niraindaruL sundara \n\n\ncaraNam    akhilalOka paripAlakanai shrI hariharar InraruL bAlakanai\npaghaivar azhiya shabari malai ezhundaruL parama dayALanai surar tozhum tALanai",
    "src": "https:\/\/karnatik.com\/c6172.shtml"
}