{
    "title": "Anandabhairavi anaiyum",
    "language": "Tamil",
    "raga": "Anandabhairavi",
    "tala": "Anandabhairavi",
    "composer": "Paapanaasam-Shivan",
    "sahitya": "Anandabhairavi anaiyun tiruvaDi malariNai tuNaiyE shankari shiv-\n\n\nanupallavi\n\n  mInam tannai nighar nIL karuNai vizhiyAl nOkki vinai nIkki aruL param-\n\n\ncaraNam    anaittuyiraiyum Inra jaganmAtA iLam kumari gowri varai\narashanarum pudalvi hari sOdari apAra krpAkari unait tozhum\nenadu vinait-tiraL aghala uLLanbODu kaDaikkaN pArAi un\nkaruNaittuLi illaiyEl Ezhaik-kulagil vEru AdhAram Edu amba",
    "src": "https:\/\/karnatik.com\/c6181.shtml"
}