{
    "title": "anbAra unnai nAn",
    "language": "Tamil",
    "raga": "husEni",
    "tala": "Adi",
    "composer": "Suddhaananda-Bhaarati",
    "sahitya": "anbAra unnai nAn alankAram sheidE en ahak-kaNNArk-kANEnO hari mAdhavA\n\n\nP:  anbAra unnai nAn alankAram sheidE en ahak-kaNNArk-kANEnO hari mAdhavA\nA:  paNbAna manadilun para vaDivai nATTiyE bhakti paravashamAgip-pAmAlai shUTTiyE\nAndhak-karaNangaLai aNimaNIyAkki Ayira nAmattAl arccanai sEvittu\nbandha dondamillA cintaiyai nivEdittu pAhi rAdhA ramaNA pAhi suguNA enrE",
    "src": "https:\/\/karnatik.com\/c7105.shtml"
}