{
    "title": "anbu sheidiDum",
    "language": "Tamil",
    "raga": "shrIranjani",
    "tala": "Adi",
    "composer": "Suddhaananda-Bhaarati",
    "sahitya": "anbu sheidiDum inbam aruLvAi Ananda shivanE agha nAyakanE\n\n\nanupallavi\n\n  vambu pEship-pEshi vAyai vIsi vIsi vanda vAzhvai vINE sindi nondiDAmal\n\n\ncaraNam    varambilAda turiya sorUpa vAnilE vAik-kOTTai kaTTi vasikkalAghumO\narum pasiyum nAvAl annam enrAl pOmO ArAindaDangi aghamukhamAgi",
    "src": "https:\/\/karnatik.com\/c7112.shtml"
}