{
    "title": "andi nEramnadik-karaiyOram",
    "language": "Tamil",
    "raga": "bhairavi",
    "tala": "Adi",
    "composer": "OotukkaaDu-VenkaTasubbaiyyar",
    "sahitya": "andi nEram nadik-karaiyOram vandu AravAram sheyyAdE sOram azhaguDan iLamayil iragonrADa nanrAga ninrADa\n\n\nanupallavi\n\n  andhamAga kuzhalUdum bAlA aravamuDi Erum rAjagOpAlA antarangamuDan \ngOpi nAn enrAlO avasarat-tAli kaTTum rAdhai maNanvALA\n\n\ncaraNam 1    aramporuL enbavai Agamam Anavai avai ivai enbadu nI nO ma dha nI \nyArum oru tuNai enbadariya oru vaghai Ala varuvadum nI nI ma dha nI\nshurudi muDi mIdu karudi naTamADum tUyavan nI tONum kadir maraiyum\nAghum muzhu matiyum pOdumunam angE pOghavENumE\n    caraNam 2    kuDattil koNarnda veNNai tinrAccu koLLai koNDa manamO unadAccu \niDam valamAi vandu idenna vambAccu ennODini irukkaTTum ini engum kATTAdE mUccu\n    caraNam 3    pinnalai pinninru izhukkalAmO adai pEccilE kETTAl maruppaLikkalAmO \nunnazhagu vizhi ennai En izhandadenru okkArum mikkArum uddhAram sheyyalAmO\n    caraNam 4    attai vITTu vazhi kETTAi attanaiyum shonnEn Attam karai vazhi kETTAi attanaiyum shonnEn \nmuttattukku vazhi kETTAl nAn enna sheivEn mOham taru pEccu ellAm vENDAmini shonnEn",
    "src": "https:\/\/karnatik.com\/c8427.shtml"
}