{
    "title": "anyaayamu sEyakura",
    "language": "Telugu",
    "raga": "kaapi",
    "tala": "aadi",
    "composer": "Tyaagaraaja",
    "sahitya": "anyAyamu sEyakurA, rAma! nanyunigA jUDakurA; nAyeDa, rAma!\n(anyAyamu)\n\n\n\n\nanupallavi\n\n\n\nennO tappulu galavArini, rAjanya! nIvu brOcinAvu ganukanu\n(anyAyamu)\n\n\n\n\ncaraNam\n\n\n\njaDa bharatuDu jinka  ishuvu netti baDalika dIrcaga lEdA?\nkaDalini muniginagirinoka\nkUrmamu kApaDAga lEdA? puDaminipANDava drOhini dharmaputruDu\nbrOvaga lEdA?\nnaDimi prAyamuna tyAgarAjanuta nA pUrvaju bAdha dIrpa\nlEnani   (anyAyamu)",
    "src": "https:\/\/karnatik.com\/c1360.shtml"
}