{
    "title": "Aratiya beLagire",
    "language": "Kannada",
    "raga": "shrI",
    "tala": "aTa",
    "composer": "Purandara-Daasar",
    "sahitya": "Aratiya beLagire\n\n\ncaraNam 1    arasi rukmiNi kUDa arasu viTTalage birudina shankhava piDida viTTalage \nsarasija sambhava sannuta viTTalage niruta iTTige mEle ninta viTTalage\n    caraNam 2    dasharatharAyana udaradi viTTala shishuvAgi janisida shrI rAma viTTala \npashupati gOpiya kandane viTTala asure pUtaniya konda viTTalage\n    caraNam 3    kaNDira bobbura venkaTavittalana aNDaja vAhana ahudO nI vittala \npANduranga kSEtra pAvana viTTalA puNDarIkAkSa shrI purandara viTTalage",
    "src": "https:\/\/karnatik.com\/c4618.shtml"
}