{
    "title": "Arudal aLikkum",
    "language": "Tamil",
    "raga": "hindOLa",
    "tala": "rUpaka",
    "composer": "Suddhaananda-Bhaarati",
    "sahitya": "Arudal aLikkum nEsanE shuddAtmanAna hrdaya vAsanE\n\n\nanupallavi\n\n  vEru vEu samaya bhEdam viTTun aruLaip-paTri ninru\nviruppilAdu veruppilAdu serukkilAdu sEvai sheyyum\n\n\ncaraNam    kuzhalaip-pOlak-konjum isaiyum kuzhandai pOlat-teLinda manamum\nezhilaip-parappum iravi nilaiyum Indananta shAntamAga",
    "src": "https:\/\/karnatik.com\/c7149.shtml"
}