{
    "title": "baja raamam sathatham",
    "language": "Telugu",
    "raga": "husEni",
    "tala": "aadi",
    "composer": "Tyaagaraaja",
    "sahitya": "bhaja rAmam satatam mAnasa\r\n(bhaja)\r\n\r\ncaraNam 1\r\n\r\namita shubhAkaram pApa timira vibhAkaram\r\n(bhaja)\r\n\r\ncaraNam 2\r\n\r\nshatamagha nuta gItam sakala shrita pArijAtam\r\n(bhaja)\r\n\r\ncaraNam 3\r\n\r\npAlita lOka gAnam parama kapAli vinuta suguNam\r\n(bhaja)\r\n\r\ncaraNam 4\r\n\r\nsarOjavara nAbham yama purArAti lAbham\r\n(bhaja)\r\n\r\ncaraNam 5\r\n\r\nvarAnanda kandam nata surAdi muni brndam\r\n(bhaja)\r\n\r\ncaraNam 6\r\n\r\nkamanIya sharIram dhIram mama jIvAdhAram\r\n(bhaja)\r\n\r\ncaraNam 7\r\n\r\nkara dhrta sharachApam rAmam bharita guna kalApam\r\n(bhaja)\r\n\r\ncaraNam 8\r\n\r\nbhava jalanidhi pOtham sArasa bhavamukha nijatAtam\r\n(bhaja)\r\n\r\ncaraNam 9\r\n\r\nvAtAtmaja sulabham vara sItA vallabham\r\n(bhaja)\r\n\r\ncaraNam 10\r\n\r\nrAja ravi nEtram tyAgarAja vara mitram\r\n(bhaja)",
    "src": "https:\/\/karnatik.com\/c1400.shtml"
}