{
    "title": "dEvI shrI",
    "language": "Tamil",
    "raga": "kalyANi",
    "tala": "kalyANi",
    "composer": "Paapanaasam-Shivan",
    "sahitya": "dEvi shrI mInalOcanni amba dIna rakSaki tenmadhuraikkadi\n\n\nanupallavi\n\n  pUvil AlavAi aranum mAlkoLap-pugazh muttamizh mozhi\n  mazhalai pazhagit-tavazhum kuzhaviyena vaLar\n\n\ncaraNam    annaiyE malayadva rAjan Inra tanNayE enaiyAL dayai nidhiyE\n ninnaiyE sharaNam ena nambinEnE nityakalyANi yAn unadaDimai",
    "src": "https:\/\/karnatik.com\/c6235.shtml"
}