{
    "title": "eppOdu pirakkum",
    "language": "Tamil",
    "raga": "sindhubhairavi",
    "tala": "Adi",
    "composer": "Kovai-Subri",
    "sahitya": "eppOdu pirakkum ippEdai pAl irakkam appanE taNi kaittala subrahmaNyanE\n\n\nanupallavi\n\n  oppilAk-karuNaiyin uraiviDamAm kaDalE ibbhuviyil aDiyArin IdillAp-pughaliDamE\n\n\ncaraNam    arupaDai vIDamarum Atral mighum vIranE Arumukha mOhana pErezil gambhIranE\nsUranai uru mATri Eru mayilAi EtravanE tArakamAghum unadu tALinaip-pOTruvanE",
    "src": "https:\/\/karnatik.com\/c8091.shtml"
}