{
    "title": "gangeyaNi",
    "language": "Tamil",
    "raga": "tODi",
    "tala": "aadi",
    "composer": "Paapanaasam-Shivan",
    "sahitya": "gangaiyaNi senjaDaiyaanaikka kaNDu kaLiyaada\r\nkaNpaDaittu menpayanpeTRaaya pEdai nenjamE\r\n(gangai)\r\n\r\nanupallavi \r\n\r\ncenkamal cEvaDiyum cengai varadaapayamum\r\ncembavaLavaayum dayai sindu maruTkaNNoondigazh\r\n(gangai)\r\n\r\ncaraNam 1\r\n\r\nkongaikulukki vevviDa kaNgaL suRaTRi manjaLaa\r\ningamnu kittiriya mangaiyan mayakkin\r\nuzhanRangu vartaman kuTTRaDa punkuzhiyun veezhndavamE\r\nkankuL pagalum suzhalum mangu tozhil viTTumadi\r\n(gangai)\r\n\r\ncaraNam 2\r\n\r\nsengamalai sh.arOtpal mangai uruvavoru\r\nsingavaNai mEyavanai kankuliDai anbar poruTTu\r\ningidamaay paNpuraitta tungiviDai vaahananai\r\nangajanuDan azhiya kaNkanarai cintummati\r\n(gangai)\r\n\r\ncaraNam 3\r\n\r\nvaasananahandaiyunaal mOsamuRavanbu seyum\r\nraajan mugaguntanuDan kaasiniyul vandavanai\r\ndEsan pugazhaaroor nagar vaasanai eesanai raama\r\ndaasan paNiyum shreetyaagaraajanai meyyanbuDanE\r\n(gangai)",
    "src": "https:\/\/karnatik.com\/c1507.shtml"
}