{
    "title": "hasiveyAgutide",
    "language": "Kannada",
    "raga": "kApi",
    "tala": "Eka",
    "composer": "Purandara-Daasar",
    "sahitya": "hasiveyAgutide amma kELe hasanAda avalakki bella kalasi koDe\n\n\nanupallavi\n\n  bisi bisi anna kai suDutide badiyalli kUDe\n\n\ncaraNam 1    khARa sAru mADa bEDa uNNarAlene enage sIsAru mADidare bEgenumbuve\n    caraNam 2    tODa tuppa hAkidare nelake ottuve enage gaTTi tuppa hAkidare bEga nunguve\n    caraNam 3    nIru mosaru hAkidare nelake ettuve enage gaTTi mosaru hAkidare taTTa nunguve\n    caraNam 4    taTTanELo krSNarAya baTTalu toLadEnu ninage ukkuva hAlina keneya kaiyali koTTu kaLuhuvenu \n    caraNam 5    kandarella kareya bandharamma kELe bALe haNNu bella cUru kaiylli koDe\n    caraNam 6    kandarella kareya bandaru tAyi kELe sakkare kobbariya kuTTi seragili hAke\n    caraNam 7    vrndAvanadoLge bandu amma kELe balu candada gombeya hUDi kaTTi koDe\n    caraNam 8    oLage ADu oLage ADu bArO ranga alli horage bUci mukhada huli tirugutide\n    caraNam 9    Odi bAro Odi bAro purandara viTTala alli Adina mukhada huli tirugutide",
    "src": "https:\/\/karnatik.com\/c4935.shtml"
}