{
    "title": "idhi neeku meragaadhuraa",
    "language": "Telugu",
    "raga": "punnaagavaraaLi",
    "tala": "aadi",
    "composer": "Tyaagaraaja",
    "sahitya": "idi nIku meragAdurA shrI rAma nAmadi tallaDillEnurA\n\n\n\nanupallavi\n\n\n\npadilamuga golicitE bhAvamu vErE unnadi\n\n\n\ncaraNam 1\n\n\n\ngati leni vArini gadatErcu daivamani patitapAvana nammiti shrI rAma \n\n     ninnati vEgamuna vEDiti santata sammatini ninnE kOriti shrI rAma\n\n\n\ncaraNam 2\n\n\n\nparama dayALuvani pAlana sEtuvani saraguna dEvarAya gOlvina nApai \n\n     karuNa lEdani kannIrAye jUci nI manasu karaga dendukurA O sItArAma\n\n\n\ncaraNam 3\n\n\n\nanniTa niNDina adbhUtAnanda ghana mannana sEya rAdA shrI rAma nI-\n\n     kennarAni puNyamu rAdA shrI tyAgarAja sannuta nIvADanu gAdA shrI rAma!\n\nsItArAma",
    "src": "https:\/\/karnatik.com\/c2347.shtml"
}