{
    "title": "inka yOcana",
    "language": "Telugu",
    "raga": "ghanTa",
    "tala": "aadi",
    "composer": "Tyaagaraaja",
    "sahitya": "inka yOcana ayitE nE nEmi sEyudurA\n\n\n\nanupallavi\n\n\n\npankajAkSa nIvaNTi parama dayAnidhi nI\n\n\n\ncaraNam 1\n\n\n\ntIrarAni pOrAye sAreku mEnu sagamAye\n\n     nEramEmO teliyadAye yAradi kika tALadAye\n\n\n\ncaraNam 2\n\n\n\n shrIpati ennikala lEni tApatrayamula nalasiti gAni-\n\n    pApa ganamu lanniyu purusuni rUpamai bAdhincEgani\n\n\n\ncaraNam 3\n\n\n\nvAgAdhipa vandya ninnE gAni orula nammani \n\n    tyAgarAjunipaini bAgAye shrI rAmaA nI",
    "src": "https:\/\/karnatik.com\/c2356.shtml"
}