{
    "title": "kaddu lEdani",
    "language": "Sanskrit",
    "raga": "jayanArAyaNi",
    "tala": "Adi",
    "composer": "Veenai-Kuppayyar",
    "sahitya": "kaddu lEdani ikanu nAtO gaTTi gAnu balkaka rAdA\n\n\nanupallavi\n\n  saddu sEyakunnAvadEmi sArasAkSa nannika brOcEti\n\n\ncaraNam 1    anya cintalu mAnihausu mIra nI sannidhAnamuna sadbhakti tODa \npannagAnu nIpai padamulanu bADucunna nA vesaTalanniya mAnpuTa\n    caraNam 2    taramugAni bAdha tALAjAlakanu karugucunna nApai karuNa jUDa \nkAlaharaNa mEla murAri prEma mIra karamu baTTi nannu kApATuDa\n    caraNam 3    bAla prAyamu nADAdigA nIdu pada sEvajEyu cunnA vENugOpAla \ndAsuni prArabdamulanu pApi bAgu mIra pAlincuTa",
    "src": "https:\/\/karnatik.com\/c4326.shtml"
}