{
    "title": "kanjadaLAyatAkSi",
    "language": "Sanskrit",
    "raga": "manOhari",
    "tala": "Adi",
    "composer": "Muttuswaamee-Dikshitar",
    "sahitya": "kanjadaLAyatAkSi kAmAkSi kamalA manOhari tripurasundari\n\n\nanupallavi\n\n kunjara gamanE maNi maNDita manjuLa caranE \nmAmavashiva panjarashuki pankajamukhi guruguha ranjani niranjani durita bhanjani\n\n\ncaraNam   rAkA shashi vadanE suradanE rakSita madanE ratna sadanE \nshrI kAncana vasanE surasanE shrNgArAshraya mandahasanE \nEkAnEkAkSari bhuvanEshvari EkAnandAmrtajhari bhAsvari \nEkAgra manOlayakari shrIkari EkAmrEsha grhEshvari shankari",
    "src": "https:\/\/karnatik.com\/c5747.shtml"
}