{
    "title": "kaNNeDuthagilum",
    "language": "Tamil",
    "raga": "simhEndra-madhyamam",
    "tala": "aadi",
    "composer": "Suddhaananda-Bhaarati",
    "sahitya": "kaNNeDuttAgilum kAnIrO en tAviya mAlaiyaip-pUNIrO\r\n\r\n\r\n\r\nanupallavi\r\n\r\n\r\n\r\npaNNum panuvalum bharatamum viratamum bhaktiyum koNDingE nittiyam\r\n\r\ntozhum ennai \r\n\r\n\r\n\r\ncaraNam\r\n\r\n\r\n\r\npErukkum pugazhukkum pErAshai paDavillai tanga padakkangaLai enrum nADavillai ayyA\r\n\r\neTTeTTu dikkilum Odavillai ummai idaya mOnattil anri-tEDavillai ayyA",
    "src": "https:\/\/karnatik.com\/c1622.shtml"
}