{
    "title": "kaNNaLavO swaamy",
    "language": "Tamil",
    "raga": "shuruTTi",
    "tala": "aadi",
    "composer": "OotukkaaDu-VeNkaTasubbaiyyar",
    "sahitya": "kaNNaLavO swaami kaar mEni kaTTazhaga nee yendan\r\n\r\nanupallavi\r\n\r\nvaNNa malar polum cinnanciru peNgaL vandu vandu nagaipadu parai\r\n(kaNNaLavO)\r\n\r\ncaraNam 1\r\n\r\nkoi malar neela kuvalai vizhiyalE vaiyadu vaiginDrai kaNNa - cinna\r\nkaiyaLavu veNNai tandaal meiyyavum podandenDru paiya paiya vadadurai aiya yeiya yeia\r\n(kaNNaLavO)\r\n\r\ncaraNam 2\r\n\r\nOyical ozhivilladu un kaval seidaal urar yenna solluvaaro kaNNa\r\naiciyarigaL ingE vandu kuccaliTTu pOnaargaL pEcenna inimElE cececece cece ce\r\n(kaNNaLavO)",
    "src": "https:\/\/karnatik.com\/c1489.shtml"
}