{
    "title": "koLLAda Ashai uNDAghudE",
    "language": "Tamil",
    "raga": "bilahari",
    "tala": "cApu",
    "composer": "OotukkaaDu-VenkaTasubbaiyyar",
    "sahitya": "koLLAda Ashai uNDAghudE gOvindan kathai amudittinai koTTuginra kuvalaya \nmalarO nin tirumukha malarndu paerugiya vaNDena nAn uNDu kaLttalum migha migha\n\n\nP:  koLLAda Ashai uNDAghudE gOvindan kathai amudittinai koTTuginra kuvalaya \nmalarO nin tirumukha malarndu paerugiya vaNDena nAn uNDu kaLttalum migha migha\nA:  uLLE oLi kANum jnAnigaLum nalla uttamat-tavam koNDa yOgigaLum \ntaLLAdaviyan caturavEdigaLum dharmam tanai koNDa nItigaLum\n\t\t\t\t(madhyamakAla)\ntaLLappaDAda iyalinait-taLLi tavam payanum taLLi migha migha varum dharmamum \nkarmamum tAnE tAnAi uNarvoDu payil kalai taliyAghiya padaviyait-taLLi yadukulamenum \nAyarpADiyil tayirO tayirena vilai kUriDum sattAghiya nark-kathaiyinil migha migha",
    "src": "https:\/\/karnatik.com\/c8557.shtml"
}