{
    "title": "kunru tOrADum",
    "language": "Tamil",
    "raga": "tODi",
    "tala": "Adi",
    "composer": "Suddhaananda-Bhaarati",
    "sahitya": "kunru tOrADum guhaik-kaDalE manam kuLirap-pozhiginra aruT-punalE\n\n\nanupallavi\n\n  manru tOrum mANikka jyOtiyin mangala dIpamE shenkadir vElanE\n\n\ncaraNam    uvamaikk-aDangAda uraiyinukk-eTTAda Unak-kaN ariyAda jnAnak-kaNNoLiyE\nkAntA shuddhAnandA Om kArtikEyA gAngEyA kalApa mayil vEl murugA murugA murugA murugA",
    "src": "https:\/\/karnatik.com\/c7487.shtml"
}