{
    "title": "mA ramaNu",
    "language": "Sanskrit",
    "raga": "rItigauLa",
    "tala": "Adi",
    "composer": "Veenai-Kuppayyar",
    "sahitya": "mA ramaNu nI varamu mAkEmi vicAramu\n\n\nanupallavi\n\n  krUrapAda kulatO jata gUDamu koncepu narulanu koniyADamu\n\n\n caraNam 1    parulalaina madilOna tiTTamu parama ghAtakAni koTi gaTTamu \nvara dhana vantula katapa meTTamu valaci anya bhAmala cEbaTTamu\n    caraNam 2    hari bhaktulatO nEStamu sEtumu apaninyalu palka venatIgatumu \nkarivaradAyani gantulu vEtumu kAla bhaTula meTa baTTi dOtumu\n    caraNam 3    peddalatO kallalATamu prItilEni tAvu tongi cUTamu \nkoddi sampadalaku narulanu bATamu gOpAla dAsula viTanADamu",
    "src": "https:\/\/karnatik.com\/c4333.shtml"
}