{
    "title": "malagayya jalajanAbha",
    "language": "Kannada",
    "raga": "kalyANi",
    "tala": "aTa",
    "composer": "Purandara-Daasar",
    "sahitya": "malagayya jalajanAbha mANIkya mANikyadi\n\n\ncaraNam 1    AdishEShanu bandu hAsigeyAgiha vEda vinuta jagadAdi puruSa kOLo\n    caraNam 2    siri bhU durgeyaru taruNiyaru mUvaru caraNavottalike kai kaTTi nintiharu\n    caraNam 3    saruvagjnya muni vandya saruva svatantrane parama sundara purandara viTTalarAya",
    "src": "https:\/\/karnatik.com\/c5169.shtml"
}