{
    "title": "nAma dhyAnam",
    "language": "Tamil",
    "raga": "rItigauLa",
    "tala": "rItigauLa",
    "composer": "Paapanaasam-Shivan",
    "sahitya": "nAma dhyAnam sheidAl pollA nOigaL ozhindiDumE sadAshiva\n\n\nanupallavi\n\n  kAma dhyAnam sheidE namadu vAzhnNAL muzhuvadum kazhindaduvE shiva\n\n\ncaraNam    hari ayan karuNaiyAl udavu marundu anboDu nambikkai irundAl arundu\ntiri manam aDakki rAma dhyAnam sheidhAl Anandam rAma dhyAnam shiva",
    "src": "https:\/\/karnatik.com\/c6398.shtml"
}