{
    "title": "nambadiru I",
    "language": "Kannada",
    "raga": "madhyamAvati",
    "tala": "jhampe",
    "composer": "Purandara-Daasar",
    "sahitya": "nambadiru I dEha nityavalla ambujAkSana bhajisi sukhiyAgu manave\n\n\ncaraNam 1    elu rakta mAmsagaLa mEle carmada hOdige oLage malamUtrAdi krimigaLiravu \nhalavu vyAdhiya biDu pancabhUtadanADu baluhu dEhava necci keDa bEDa manuja\n    caraNam 2    sati sutaru hitarendu mati maredu mamateyali ati kAnkSeyinda durviSaya balidu \nsatata lakSmIpatiya sharaNanenade ihaparada gatishUnyanAgi nI keDa bEDa manuja\n    caraNam 3    parara nindisade para vadhugaLanu bayasade guruvipra sEveyanumADu biDade \nhari stutiya nI kELu hari kIrtaneya mADu siri purandara viTTalanolidi pAlisuva",
    "src": "https:\/\/karnatik.com\/c5258.shtml"
}