{
    "title": "naTana sabhApatiyE",
    "language": "Tamil",
    "raga": "nATakuranji",
    "tala": "nATakuranji",
    "composer": "Paapanaasam-Shivan",
    "sahitya": "naTana sabhApatiyE arivan uyar kaDana kalaiyin perumai tillai\n\n\nanupallavi\n\n  iDadu padam tUkki iLa naghaiyuDan nOkki aDiyavar iDar nIkki\nabhaya karamum varamaruL karamum ashaindAraDum\n\n\ncaraNam    tirumaghaL nAthan mrdanga nAdam dhIm takiTa jhaNakum enradhira\ndishai mukhan tALam taLAngu taLAngu enroli sheyyap-puli patanjali magizha\nvara munivarum jaya jaya vena shivakAma valliyammai iru kaNkuLira\ntudiyum Damaruvum duDhum duDhum ena viri shaDaiyum puliyuDaiyum ADa manrADiya",
    "src": "https:\/\/karnatik.com\/c6410.shtml"
}