{
    "title": "nee dhaya raavalegaaka",
    "language": "Telugu",
    "raga": "tODi",
    "tala": "aadi",
    "composer": "Tyaagaraaja",
    "sahitya": "nI daya rAvalegAka nEnenta vADanu rAma\n\n\n\nanupallavi\n\n\n\n vEda shAstra purANamulanni nIvE gati anucu morabeTTu ganuka\n\n\n\ncaraNam 1\n\n\n\n sArasAra kantAra caramada vidAra sundarAkAra suguNa \n\nsukumAra mA ramaNa nIrajAptakula pArAvAra sudhArasa pUrNa\n\n   \n\ncaraNam 2\n\n\n\n shrI harE vara vidEhajAdhipa vivAha daLita ripu dEha shESa \n\nsamabAhA sajjana samUha vairimada dAhA mauni hrdgEhA nAdupai\n\n   \n\ncaraNam 3\n\n\n\n Adi dEva dEvAdi mrgya sanakAdi vinuta kAmAdi sadguNa \n\nharAdi madhya rahitAdi tyAgarAjAdi vandita vivAdi mada haraNa",
    "src": "https:\/\/karnatik.com\/c2652.shtml"
}