{
    "title": "ninaikkAda nEramillai",
    "language": "",
    "raga": "kApi",
    "tala": "Adi",
    "composer": "Vaalee",
    "sahitya": "ninaikkAda nEramillai nenjam nekkurugi vizhi nIr perugi unnai\n\n\nanupallavi\n\n  manak-kadavait-tirandEn mUDavillai unmEl maiyal koNDEn kai kUDavillai murugA\n\n\ncaraNam    panniru kaNNazhagaip-pArttEn uLLam paravashattAl tuLLa uDal vErttEn\nunniru padam nADi innisaiyuDan pADi ODi vandEn AyyA vEl murugayyA",
    "src": "https:\/\/karnatik.com\/c9330.shtml"
}