{
    "title": "nivaaDanE gaana",
    "language": "Telugu",
    "raga": "saaranga",
    "tala": "jhampa",
    "composer": "Tyaagaraaja",
    "sahitya": "nIvADanE gAna nikhila lOka nidAna nimiSa mOrvaga galana\n\n\n\nanupallavi\n\n\n\n dEvAdi dEva bhUdEva varapakSa rAjIvAkSa sAdhu jana jIvana sanAtana\n\n\n\ncaraNam\n\n\n\n satyambu nityambu samaramuna shauryambu natyanta rUpambu amita balamu \n\nnityOtsavambu gala nIku nija dAsuDani tathyambu balku shrI tyAgarAjArcita",
    "src": "https:\/\/karnatik.com\/c2671.shtml"
}