{
    "title": "OmkAra panjara",
    "language": "",
    "raga": "rAgAmAlikA",
    "tala": "Adi",
    "composer": "Mysore-VaasudEvaacaarya",
    "sahitya": "(rAgA:  madhyamAvati)   \n\n\nanupallavi\n\n\n\nOmkAra panjara.  rAgAmAlikA.  Adi tALA.\n1:  OmkAra panjara shukIm-upaniSad-udhyAna kEli kalakaNThIm \nAgama vipnia mayUrI-mAryAmantar-vibhAvayE gaurIm\n caraNam 2  \t\t\t(rAgA:  Anandabhairavi)Aa:S G2 R2 G2 M1 P D2 P N2 S  Av:  S N2 D2 P M1 G2 R2 S  dayamAna dhIrga nayanAm dEshika rUpENa darshitAbhyudayAm \nvAmakuca nIhita vINAm varadAm sangIta mAtrukAm vandE\n caraNam 3  \t\t\t(rAgA:  kAmbhOji)Aa:S R2 G3 M1 P D2 S  Av:  S N2 D2 P M1 G3 R2 S N3 P D2 S  shyAma tanu saukumAryAm saundaryAnanda sampadunmESAm \ntaruNima karuNApurAm madajala kallOla lOcanAm vandE\n caraNam 4  \t\t\t(rAgA:  kalyANi)Aa:S R2 G3 M2 P D2 N3 S  Av:  S N3 D2 P M2 G3 R2 S  nakha mukha mukharita vINAnAda rasAsvAda nava navOllAsam \nmukhamamba mOdayatu mAm muktA tATanka mugda hasitam tE\n caraNam 5  \t\t\t(rAgA:  mAyAmALavagauLa)Aa:S R1 G3 M1 P D1 N3 S  Av:  S N3 D1 P M1 G3 R1 S  sarigama pada niratAm tAm vINA sankrAnta kAnta hastAm tAm \nshAntAm mrduLa svAntAm kucabharatAntAm namAmi shivakAntAm\n caraNam 6  \t\t\t(rAgA:  mOhana)Aa:S R2 G3 P D2 S  Av:  S D2 P G3 R2 S  avaTutaTa ghaTitacUlI tADita tAlI palAsha tATankAm \nvINA vAdana vElA kampita shirasam namAmi mAtangIm\n caraNam 7  \t\t\t(rAgA:  bhairavi)Aa:S R2 G2 M1 P D2 N2 S  Av:  S N2 D1 P M1 G2 R2 S  vINA ravAnuSangam vikaca madAmOda mAdurI bhrngam \nkaruNA pUratarangam kalayE mAtanga kanyakApAngam\n caraNam 8  \t\t\t(rAgA:  simhEndramadhyam)Aa:S R2 G2 M2 P D1 N3 S  Av:  S N3 D1 P M2 G2 R2 S  maNI bhanga mEcakAngIm mAtangIm naumi siddha mAtangIm \nyauvana vana sArangIm sangItAm-bhOruhAnubhava bhrngIm\n caraNam 9  \t\t\t(rAgA:  suraTi)Aa:S R2 M1 P N2 S  Av:  S N2 D2 P M1 G3 P M1 R2 S  mEcakamAsEcanakam mithyA dhrSTAnta madhya bhAgam tE \nmAtastava svarUpam mangala sangIta saurabham vandE",
    "src": "https:\/\/karnatik.com\/c4532.shtml"
}