{
    "title": "oru kaNamAyinum",
    "language": "Tamil",
    "raga": "dEvagAndhAri",
    "tala": "Adi",
    "composer": "Suddhaananda-Bhaarati",
    "sahitya": "oru kaNamAyinum maravEnE en uLLattaik-koLLai koNDa iraivanE unnai\n\n\nanupallavi\n\n  guruvum kula deivamum koNDa maNALanum gOvardhana giridhara gOpAla sAmi nIyE\n\n\ncaraNam    siriya vayadil ennaip-piriyamuDan kaip-paTri I\\jIva nAthanAna pAvanAtItanE\narivu vandadu mudal Ashai nEsanAi unnai anbu shei mIrAvin inba maNALanE",
    "src": "https:\/\/karnatik.com\/c7640.shtml"
}