{
    "title": "pAmaruni brOva tAmasamA",
    "language": "",
    "raga": "kalyANi",
    "tala": "cmaTya",
    "composer": "Mysore-Sadaashiva-Rao",
    "sahitya": "pAmaruni brOva tAmasamA vinumA umA madagamA\n\n\nanupallavi\n\n  kAmitArtha phaladAyaki nIvani sadA kOritini ekAmrEshvaruni  rANi kalyANi\nnatajana pAlini gAnavinOdini shubhankari parAtpari bhakta vashankari\n(ciTTasvara sAhitya)\npAvani nI dayagAka nAku vErE vardani sArasAkshi nI pAda padmamula \nsAri sAri nE karuNAkariyani mrokkiti brOvavammA dayatOnu\n\n\ncaraNam    tallI brOva bhAramA nata kalpavalli nI dAsuDugadA parIksha jEyakavE \nkAmAkshi nIdu kaTAksha vIkshaNAmruta prOkshaNatO kavi sadAshivuni \nbhava harinchuTaku manchi samayamidi shiva nAyaki varadAyaki anishamu\npADinA ninu vEDinA rAvavA nEDu kOrina vEDukala dIrcavA\nbhavAni vEgamE brOvu sarOja nayani pinAkadharuni manas-sadani",
    "src": "https:\/\/karnatik.com\/c8877.shtml"
}