{
    "title": "paNNina pAvam",
    "language": "Tamil",
    "raga": "kApi",
    "tala": "Adi",
    "composer": "Kovai-Subri",
    "sahitya": "paNNina pAvam yAvum parandODip-pOghumE aNNal Arumukhanai aDaikkalam aDaindAl\n\n\nanupallavi\n\n  maNNulaga vAzhvil manam magizhndiDavE eNNip-perap-pENum inba sukham uNDAgum\n\n\ncaraNam    vanna mayilOnadu nannigharE illAda ponnaDit-tuNaiyAl innalaip-pOkkalAm\ncennai nagaram Onga sEvark-koDi tAngi annai pOl anbarai aNaivOnaip-paNindAl",
    "src": "https:\/\/karnatik.com\/c8231.shtml"
}