{
    "title": "paramAnanda sukham",
    "language": "Tamil",
    "raga": "shuddhadhanyAsi",
    "tala": "Adi",
    "composer": "Kovai-Subri",
    "sahitya": "paramAnanda sukham tarumE muruga nAmam pAril avadiyuruvOrin kavalai tIrum\n\n\nanupallavi\n\n  siridEnum anudinam cintai sidarAmal nirutti adaik-karudi varuvOrukkellAm\n\n\ncaraNam    kAsu paNa mOhattAl mOsam pOghum manadu vIsum kOpattAl vimmi veDikkAdu\nmAsu paDiya mayakkum Ashaip-pishAcukkadu dAsanAgiDAmal vimOcanam aLikkum",
    "src": "https:\/\/karnatik.com\/c8233.shtml"
}