{
    "title": "pazani ninra",
    "language": "Tamil\r\n\r\nviruttam\r\n\r\ntEn pazhani vElavanE\r\nen manattin oLi viLakkaay\r\nenrum ninravanE\r\nmangil naDamaaDungra\r\nmaadEvan satguruvE",
    "raga": "kaapi",
    "tala": "roopakam",
    "composer": "Periyasaami-Tooran",
    "sahitya": "pazhani ninDra paraman tanda\r\npazhama daana deivamE\r\n(pazhani)\r\n\r\nanupallavi \r\n\r\nazhagu deivam aruLil deivam\r\nkuzhandai deivam kumara deivam\r\n(pazhani)\r\n\r\ncaraNam \r\n\r\nkaadal vaLLi kaNDa deivam\r\nkaNNin maNiyaay ninDra deivam\r\nvEdam pOTrum gnyaana deivam\r\nvENDuvOrai kaakum deivam\r\n(pazhani)",
    "src": "https:\/\/karnatik.com\/c1501.shtml"
}