{
    "title": "pratyangirA bhagavatim",
    "language": "Sanskrit",
    "raga": "nAdanAmakriya",
    "tala": "cApu",
    "composer": "Muttuswaamee-Dikshitar",
    "sahitya": "pratyangirA bhagavatim sadA namAmyaham prabala sihma vAhArUDhAm\n\n\ncaraNam   nityam shivabhakta varadAm nikhila janAdi nuta nija padAm nitya shuddha \nparamAnandAm nija guruguha mOda kumudAm shaktyAdi samUhAkArAm sharabhEsha \nmada haraNa caturAm kSityAdi tatvAnta rUpAm kSamkArAnanda vilEpAm",
    "src": "https:\/\/karnatik.com\/c5864.shtml"
}