{
    "title": "sA vAmA ruSA",
    "language": "",
    "raga": "khamAs",
    "tala": "Adi",
    "composer": "Swaati-TirunaaL",
    "sahitya": "sA vAmA ruSA  yAtu mAnanIya yA sAmAnyA ramAyA mA\n\n\nanupallavi\n\n  pAvanAmbhOja nAbha parAdhInatAm aham tAvakI majAnanA tApAya sadA jAtA\n\t\t\t\t(svara sAhitam)\nsA nIti vimalAdhamAla mahAmAgasA samayamapi nahi tasyA avitannIti dhurandhara\nmatta nAga kAmini  tathA siki mutApamiha mAnasa manuvidhi sa nidhi patI girisha sumadita mrdupari\n\n\ncaraNam    dAmOdara jAnAmi\n\t\t\t\t(svara sAhityams)\n1. vAmAla pAniha mama\n2. manidarpana vidhu pAdapa rakha kavidhA vivada mAyA pi mA sAmAni\n3. dhAtru krpA pada  mAdhava vadatidhuni tava bahudhA \nbhavatihi kimu vahasi mudAtaramiha himagiri sama\n caraNam 4    sAma gamanI vimukha muni sArasabisi nI dayitapada mA shumA \nkalaya mama mama visru japataka kula pati ratha kapaTa gati catura \nsatyAdhanIya pada nirNIta hIna guNa baddhAnu rga kAmaddAvidhAya \nviphalAmiha kathamAgama nilaya karuNArasa rahitObha vAnajani   \n caraNam 2    dAmOdara jAnAmi tAvakAshayam mayi janakatE mukha mA janaya vitOSam",
    "src": "https:\/\/karnatik.com\/c6903.shtml"
}