{
    "title": "sArasa sama mrdupada",
    "language": "",
    "raga": "gaurImanOhari",
    "tala": "Adi",
    "composer": "Swaati-TirunaaL",
    "sahitya": "sArasa sama mrdupada nIti nilaya jaya jaya jalajayanAbha harE vasa mama hrdi\n\n\nanupallavi\n\n  mAra janaka suramuni sEvya kSIrAmbudhi kalita shayana shrI\n\n\ncaraNam 1    sAmaja parivrDha bhava haraNAhita jAla vinAshana cAru guNa \nsadanakAmita dAna parAyaNa nArada shaunaka sannuta shrI\n    caraNam 2    bhUri krpArasa vAsa vibhO paripAhi ramAdhava bhAsura \ntanusuSama shArata shashi mukha kaustubha hAra ravi vidulOcana\n    caraNam 3    vAraya pApa samUham danujALi vibhanjana pAvana carita\ndArita madhu mukha rAkSasa sancaya viracaya shapamayi vasa hrdi mama",
    "src": "https:\/\/karnatik.com\/c6930.shtml"
}