{
    "title": "sArasa pUmpAdam",
    "language": "Tamil",
    "raga": "behAg",
    "tala": "Adi",
    "composer": "Paapanaasam-Shivan",
    "sahitya": "sArasa pUmpAdam paNivOm samsAra van-tApam tAn taNivOmE\n\n\nanupallavi\n\n  nIraja viSaya viSattanai uNDu nilaiyillAda ulaga inbamE peridenru ninaindu magizhndadu pOdumE\n\n\ncaraNam    angumingum engumE niraindavan anbillArkku illAdi maraindavan akhila ulaguyirum paDaittaLitt-azhippavan anaittuyirkkum annai tandaiyAi tazhaippavan aruLE vaDivAi aDiyAr uLLamE tiru mALigaiyAi aghalAduraivOn oru pErilan Ayiram pEruDaiyAn karuvAdanai tIravum nam iraivan",
    "src": "https:\/\/karnatik.com\/c6487.shtml"
}