{
    "title": "shrI mInAmbikayA",
    "language": "Sanskrit",
    "raga": "dEvagAndhAri",
    "tala": "rUpaka",
    "composer": "Muttuswaamee-Dikshitar",
    "sahitya": "shrI mInAmbikAyA param nahi rE rE citta nityam kAmEshvaryArAdhita paradEvyA\n\n\nanupallavi\n\n sOma sundarEshvara mOhinyA malayadhvaja pANDya rAja praNata \nsharanyAyA nAma rUpa pArAyaNa priya rAja yOginyA\n\n\ncaraNam   nAda bindu kalAspada rUpiNyA navaratna vINA vAdinyA shrI \ndEvagAndhAri pUjitAmbujAsinyA kadambavana vilAsinyA guruguha jananyA",
    "src": "https:\/\/karnatik.com\/c5951.shtml"
}