{
    "title": "sundhari ninnu",
    "language": "Telugu",
    "raga": "aarabi",
    "tala": "caapu",
    "composer": "Tyaagaraaja",
    "sahitya": "sundari ninu varNimpa brahmAdi surulakaina taramA\n\nanupallavi\n\n kundaradanE sanandanAdi vanditE nE nenta tripura\n\ncaraNam 1\n\n kala kalamanu mukha kaLalanu gani kaluvala rAju bhuviki rADAye celagu nI lAvaNyamunu \ngani alanADE valarAju gAnaka pOye nilu varamagu nI ghambIramunu gani jalarAju jaDa \nvESuDAye balamaina dhIratvamunu gani  kanakA-caluDu tA shila rUpuDayE tripura \n   \ncaraNam 2\n\n kanulanu gani siggubaDi gaNDu mInulu vanadhi vAsamu sEyanAyE janani nI ciru navvu \nkAnti soki shivuDa-nupamamau shubhruDAye minuku sommula cEla kAntula mErupula kani \nnimiSamu niluvadAye kanakAngi nI svaramunu vini vANi magani jihvanu tA pUnikAyai tripura\n   \ncaraNam 3\n\n pAvanamanu sEyu biriduni gani bhakta pApamu pAripOnAye EvELa nI dayacEta \nsat-kavulella kAvyamulanu shEyanAyE mAvaruniki cellElanu santOSamuna dEvi peddalu \nbalkanAye bhAvinci nI pAdamuna tyAgarAju bhAvuka manu konanAye tripura",
    "src": "https:\/\/karnatik.com\/c2883.shtml"
}