{
    "title": "swamikki seri",
    "language": "Telugu",
    "raga": "bEgaDa",
    "tala": "roopakam",
    "composer": "Tyaagaraaja",
    "sahitya": "sAmiki sari jeppa jAla vElpula rAma\n\nanupallavi\n\n nA manasu natanipai nATi uNDaga norula\n\ncaraNam 1\n\n eTi yOcana cAlu nevvari kETulO vrAlu mATalADutamElu madi kidE padivElu\n   \ncaraNam 2\n\n tana kaNTi kentO muddu tappa DADina paddu canuvu jEyu nE proddu callani\njUpu kaddu\n   \ncaraNam 3\n\n anni vElpula lOna natani sarigAna tannu brOcina ghana tyAgarAja\nsakhuDaina",
    "src": "https:\/\/karnatik.com\/c2803.shtml"
}