{
    "title": "tangi nODe",
    "language": "Kannada",
    "raga": "kEdAragauLa",
    "tala": "aTa",
    "composer": "Purandara-Daasar",
    "sahitya": "tangi nODe nammangaLadoLu pANduranga mellaDi iTTU pOdanamma\n\n\ncaraNam 1    gange janisi mUrlOkakke mukutiyu tA rangavoliva pAda mangaLa \nsAsira daLada sarvOttama rangavalliya nikkidante shObhisutide\n    caraNam 2    siriyaja bhavarugaLarasi kANaru siri caraNa pUrita beLagutide vara vajrAnkusha \ndhvaja Urdhava rEkheya nODi dharaNikAbharaNa viTTante shObhisutide\n    caraNam 3    hindidAnanda janmada pApake kEDu mundaNAnanda sukrtake jODu \ntande purandara viTTalarAya suLidu hinde munde kOTi kulavanuddharisida",
    "src": "https:\/\/karnatik.com\/c5525.shtml"
}