{
    "title": "thillana (tham thana dhirana)",
    "language": "Telugu",
    "raga": "kEdaara-gowLa",
    "tala": "aadi",
    "composer": "Walajapet-Venkatramana-Bhaagavatar",
    "sahitya": "tAm tanA dhirana tana dhiranA dhiri tAm dhiranA dhira tana dhiranA\n\nanupallavi\n\n tAm tAm dhiri dhiri nAdhiri dhirdhir tillAnA dhiritaka tillAna \ntillAna dhiri tillAna dhiri tillAna dhiri tanadhira nAdira\n\nsholkaTTu\n\ntajjhaNu jhaNutaka dhimikiTa tarikiTa tAm tarikiTa taka tadingiNa takadhimi \ntaLAngu taka taLAngutaka tadingiNatOm tadingiNatOm tadingiNatOm giNatOm\n\ncaraNam\n\n bhaktulella jUci santasilla bAluDavai kAlikejjalu mrOyaga \nbAguga nADucu vENugAnamutO eduTarA mrokkedarA\nmukti dAyakuDau nIvanucununE mOhanAnga nI pAda yugamula \nmOdamavara nanninAnu brOvumu murAsura narakAdi ripu vidArA\nrAmacandrapura vara rAjagOpAla dEva shrI mahAnubhAva\n\t\t(repeat sholkaTTu, then pallavi)",
    "src": "https:\/\/karnatik.com\/c3220.shtml"
}