{
    "title": "thillaana (bhaagEshri)",
    "language": "",
    "raga": "bhaagEshri",
    "tala": "khaNDa-caapu",
    "composer": "TK-Rangacaari",
    "sahitya": "dhirana dhIm ta dhIm dhirana nAdhru dhru tAni nAdhru dhIm tOm\n\ndhrutIm dhIm dhIm tana dhirana \n\n(dhira)\n\n\n\nanupallavi\n\n\n\ntaddhina dhina dhIm dhirana dhimi takiTa takiTajam\n\nnAdhru tAni tomdhru tAni jomta jomta jom tadhingiNatom\n\n(dhirana)\n\n\n\ncaraNam\n\n\n\nPoi adanai meyyenru pEshittirinda nI meipporuL onradanai En\n\nmarandAi\n\nsheipporuL ellAm avan sheyal enreNNU shivakAmi nEshanai\n\nsabEshanai tudi paNNu\n\n\n\nsholkaTTu\n\n\n\ndhIm takiTa nom takiTa kiTa taLAngu taka jom jham tanita nom\n\ntarita jhoNu takiTa dhIm dhIm\n\ntatti trkiTa tOmtaka taLAngu jham takiTa jom jom takiTa jhamta nam tari takiTa tarita\n\nnAdru tom drudru tOm taka nanku Dingu takaNaka takataLAngu\n\ntakataLAngu takataLAngu taka \n\n(dhirana)",
    "src": "https:\/\/karnatik.com\/c1261.shtml"
}