{
    "title": "thwamEva saraNam",
    "language": "Telugu",
    "raga": "pahaaDi",
    "tala": "aadi",
    "composer": "Annamaacaarya",
    "sahitya": "twamEva sharaNam twamEva sharaNam \n\nkamalOdhara shree jagannaataa\n\n(twamEva)\n\n\n\ncaraNam 1\n\n\n\nvaasudEva krishNa vaamana narasimha\n\nshree sateesa sarasija netraa\n\nbhoosuravallabha purushOttama\n\npeeta kowsEyavasana jagannaataa\n\n(twamEva)\n\n\n\ncaraNam 2\n\n\n\nbalabadraanuja paramapurusha dugdha\n\njaladhivihaara kunjaravaradaa\n\nsulabha subadraa sumukha surEswara\n\nkalidOshaharaNa jagannaataa\n\n(twamEva)\n\n\n\ncaraNam 3\n\n\n\nvaTapatra sayana bhuvanapaalana jantu\n\nghaTakaara karaNa srungaaradhipaa\n\npaTutara nityavaibhavaraaya tiru\n\nvEnkaTagirinilaya jagannaata\n\n(twamEva)",
    "src": "https:\/\/karnatik.com\/c1576.shtml"
}