{
    "title": "thyaagaraaja sadhguru",
    "language": "",
    "raga": "hindOLam",
    "tala": "roopakam",
    "composer": "HN-Muttayyah-Bhaagavatar",
    "sahitya": "tyAgarAja sadguruvani dalacavE O manasA\n\n\n\nanupallavi\n\n\n\n bhAgavata varENyulaina parama shAnta bhakta sadana \n\n\n\ncaraNam 1\n\n\n\nkAvERi tIramuna shrIkara pancanadapuramuna bhU vara shrI rAmabhahma putruDugAna-\n\nvadarinci shrI vAlmIkyAncuDane telpinaTTu tArakakai pAvanamagu rAmAmrta pAnamucE santasillina\n\n\n\ncaraNam 2\n\n\n\nnAdasvarArNava shAstramu nAraduDanu grahimpaga bhEda rahitamagu tana sangItamucE\n\n mAnavulaku mOdamaina krtula cEsi mOkSa phalamidaniccina vEda mUrti pAda bhakti migilinavA\n\n\n\ncaraNam 3\n\n\n\ndharaNilO janiyincina tana janmamu nIDOra tombatyAru kOTi rAma nAmamantarangamuga\n\n japinci parama pApa harikEshAptuDaina nAyantarangamu nelakonna",
    "src": "https:\/\/karnatik.com\/c2138.shtml"
}