{
    "title": "vandadellAm",
    "language": "Tamil",
    "raga": "husEni",
    "tala": "husEni",
    "composer": "Paapanaasam-Shivan",
    "sahitya": "vandhadellAm varaTTum anda kandan krpai maTTum irukkaTTum\n\n\nanupallavi\n\n  manda manadu bhava bandha vinaiyiluzhanru\nenda vELaiyilum varunda sheyya maTTum anRi\n\n\ncaraNam    ulagamellAm nammai pazhikkaTTum ghana uzhvinaiyAl tuyar shezhikkaTTum pala\nkavalaigaLoDu shila nimiSam murugan parama krpaiyai ninaindurugi bhajanai seyvOm\nvaNDAr kuzhal (viruttam).   \nvaNDAr kuzhal mAdumaiyAL pUngarattAl varuDum tiruppAdam\ntoNDar paNikkup-paravaimanai tUdu naDanda tirup-pAdam\nviNDa aDiyArkkuLam kanindu parindu vIDu tarum pAdam\nkoNDa naTana tirup-pAdam koNDen manadil UyndEnE",
    "src": "https:\/\/karnatik.com\/c6596.shtml"
}