{
    "title": "vasundharA tanaya",
    "language": "",
    "raga": "bhairavi",
    "tala": "cempaT",
    "composer": "Swaati-TirunaaL",
    "sahitya": "vasundharA tanayaAdhava pAlaya vAsavAdi natapadA krpAlaya\n\n\nanupallavi\n\n  vAsAnisham mama jagadIshvara vairijAla dharacApa vishikhadhara\n\n\ncaraNam 1    hEma cAru ruci madahara nirupama cEla hita sajjana samudaya pAla dasha kANTha vinAshana kAmakOTi sundarapata natajana kAma dAyaka kaTAkSa nirIkSaNa himakara sama ruci vadana parilasita\n    caraNam 2    vIrakIsha gaNa parivrta durita nirAsa viditamala guNa mrduhASa manu vamsha vibhUSaNa \npArijAta suma vAsita kaca bhara sharadAmburuha nEtra yugAmala dinakara suta bhayahara \n    caraNam 3    nIla kAnti ghana vijaya caNAtbhuta dEha nrvarAhishama laghu bAha jita bhArgava mOhana bhAla lAlasita sundara mrgamada padmanAbha puruSOttama jaya ayakuru mama shubhamayi dinamanu raghuvara",
    "src": "https:\/\/karnatik.com\/c6997.shtml"
}