{
    "title": "veLLI nilavinilE anda teLLa nilai tanilE",
    "language": "Tamil",
    "raga": "aThANA",
    "tala": "rUpaka",
    "composer": "OotukkaaDu-VenkaTasubbaiyyar",
    "sahitya": "veLLI nilavinilE anda teLLa nilai tanilE kaNNan vENugAnam pADinAn uLLam \nvENum vENumenru AdinAn anda vindai mukham kANa nangaiyarum angu kUDinAr\n\n\nanupallavi\n\n  Allip-pozhiginra AnandamAna ayyanivai kaNDu pADinadAna \nuLLapaDitAnum uyvadumAna yOga mAyai angu nADinadAna\n\n\ncaraNam    vELai tanil nishi vELaiyum uyya vENakalaigaLum yAvaiyum uyya \nnALaiyum pinnarum yAvarum uyya nADi vanda anda nangaiyar meyya \nshuttip-parai tarattO maram illai tUdu shenru vara tOzhanumillai viddai \nennavenrAl shollavum vallai cinna vENugAnam anri vEronrum illai",
    "src": "https:\/\/karnatik.com\/c8750.shtml"
}